pearlcli-2.1.1.data/scripts/pearl
pearlcli-2.1.1.dist-info/METADATA
pearlcli-2.1.1.dist-info/RECORD
pearlcli-2.1.1.dist-info/WHEEL
pearlcli-2.1.1.dist-info/top_level.txt
pearllib/__init__.py
pearllib/exceptions.py
pearllib/messenger.py
pearllib/package.py
pearllib/parser.py
pearllib/pearl.py
pearllib/pearlenv.py
pearllib/system.py
pearllib/utils.py
pearllib/static/boot/emacs/pearl.el
pearllib/static/boot/fish/pearl.fish
pearllib/static/boot/sh/pearl.sh
pearllib/static/boot/vim/pearl.vim
pearllib/static/buava/.git
pearllib/static/buava/.gitmodules
pearllib/static/buava/.travis.yml
pearllib/static/buava/CONTRIBUTING.md
pearllib/static/buava/LICENSE
pearllib/static/buava/README.md
pearllib/static/buava/lib/osx-compat.fish
pearllib/static/buava/lib/osx-compat.sh
pearllib/static/buava/lib/trycatch.sh
pearllib/static/buava/lib/utils.sh
pearllib/static/buava/tests/bunit/.git
pearllib/static/buava/tests/bunit/bin/checkstyle.sh
pearllib/static/buava/tests/bunit/bin/unit-tests.sh
pearllib/static/buava/tests/bunit/utils/shunit2
pearllib/static/buava/tests/bunit/utils/utils.sh
pearllib/static/buava/tests/test-utils/.git
pearllib/static/buava/tests/test-utils/utils.sh
pearllib/static/buava/tests/test-utils/installs/install-bash.sh
pearllib/static/buava/tests/test-utils/installs/install-fish.sh
pearllib/static/buava/tests/test-utils/installs/install-git.sh
pearllib/static/buava/tests/test-utils/installs/install-linux-deps-fast.sh
pearllib/static/buava/tests/test-utils/installs/install-linux-deps.sh
pearllib/static/buava/tests/test-utils/installs/install-osx-deps-fast.sh
pearllib/static/buava/tests/test-utils/installs/install-osx-deps.sh
pearllib/static/buava/tests/test-utils/installs/install-zsh.sh
pearllib/static/buava/tests/test-utils/integ-tests/default-integ-tests.sh
pearllib/static/buava/tests/test-utils/integ-tests/default-travis.yml
pearllib/static/buava/tests/test-utils/integ-tests/integ-tests.fish
pearllib/static/buava/tests/test-utils/integ-tests/integ-tests.sh
pearllib/static/buava/tests/unit-tests/test-osx-compat.fish
