Metadata-Version: 2.1
Name: pearlcli
Version: 2.1.1
Summary: Pearl is a lightweight package manager for automating reproducible environments between different systems (Linux and OSX).It can be used for dotfiles, plugins, programs and any form of code accessible via git.
Home-page: http://github.com/pearl-core/pearl
Author: Filippo Squillace
Author-email: feel.sqoox@gmail.com
License: GNU General Public License v3
Download-URL: https://github.com/pearl-core/pearl/releases
Keywords: pearl,shell,dotfiles,package manager
Platform: UNKNOWN
Classifier: Development Status :: 5 - Production/Stable
Classifier: Intended Audience :: Developers
Classifier: Programming Language :: Python :: 3
Classifier: Programming Language :: Python :: 3.5
Classifier: Programming Language :: Python :: 3.6
Classifier: Programming Language :: Python :: 3.6
Classifier: Programming Language :: Python :: 3.7
Classifier: Programming Language :: Python :: 3.8
Classifier: Natural Language :: English
Classifier: License :: OSI Approved :: GNU General Public License v3 (GPLv3)
Classifier: Operating System :: MacOS
Classifier: Operating System :: POSIX :: Linux
Classifier: Topic :: Software Development :: Build Tools
Classifier: Topic :: System :: Software Distribution
Classifier: Topic :: System :: Shells
Classifier: Topic :: Utilities
Requires-Python: >=3.5
Provides-Extra: dev
Provides-Extra: dev
Requires-Dist: coverage; extra == 'dev'
Requires-Dist: flake8; extra == 'dev'
Requires-Dist: pip; extra == 'dev'
Requires-Dist: pytest; extra == 'dev'
Requires-Dist: Sphinx; extra == 'dev'
Requires-Dist: tox; extra == 'dev'
Requires-Dist: twine; extra == 'dev'
Requires-Dist: watchdog; extra == 'dev'
